README.rst
setup.py
py2rb/__init__.py
py2rb/formater.py
py2rb.egg-info/PKG-INFO
py2rb.egg-info/SOURCES.txt
py2rb.egg-info/dependency_links.txt
py2rb.egg-info/entry_points.txt
py2rb.egg-info/requires.txt
py2rb.egg-info/top_level.txt
py2rb/builtins/module.rb
py2rb/builtins/require.rb
py2rb/builtins/using.rb
py2rb/modules/lib.yaml
py2rb/modules/numpy.yaml
py2rb/modules/unittest.yaml