Metadata-Version: 1.1
Name: py2rb
Version: 0.1.1
Summary: A code translator using AST from Python to Ruby
Home-page: https://github.com/naitoh/py2rb
Author: NAITOH Jun
Author-email: naitoh@gmail.com
License: MIT
Keywords: python ruby
Platform: UNKNOWN
Classifier: Development Status :: 4 - Beta
Classifier: Intended Audience :: Developers
Classifier: Topic :: Software Development
Classifier: License :: OSI Approved :: MIT License
Classifier: Programming Language :: Python :: 3
Classifier: Programming Language :: Python :: 3.5
Classifier: Programming Language :: Python :: 3.6
